tushell/__init__.py
tushell/core.py
tushell/curating_red_stones.py
tushell/echo_sync_client.py
tushell/echoform_crystallography.py
tushell/echonode_trace_activation.py
tushell/enriched_version_fractale_001.py
tushell/graphbuildersync.py
tushell/issue_indexer.py
tushell/lattice_drop.py
tushell/orchestration.py
tushell/redstone_writer.py
tushell/reflexql.py
tushell/trinity_superecho.py
tushell/tushellcli.py
tushell-0.2.20.dist-info/METADATA
tushell-0.2.20.dist-info/WHEEL
tushell-0.2.20.dist-info/entry_points.txt
tushell-0.2.20.dist-info/top_level.txt
tushell-0.2.20.dist-info/RECORD
