Metadata-Version: 2.4
Name: tushell
Version: 0.2.20
Summary: The Data Diver's best Intelligent and Narrative Command-Line Tooling you will have ever had
Home-page: https://github.com/jgwill/tushell
Author: JGWill
Author-email: JGWill <tushellframe@jgwill.com>
Project-URL: Homepage, https://github.com/jgwill/tushell
Classifier: Programming Language :: Python :: 3
Classifier: License :: OSI Approved :: MIT License
Classifier: Operating System :: OS Independent
Requires-Dist: click
Requires-Dist: requests
Requires-Dist: python-dotenv
Requires-Dist: PyYAML
Dynamic: author
Dynamic: home-page
